autopretorch/__init__.py
autopretorch/core.py
autopretorch/utils.py
autopretorch-0.1.0.dist-info/licenses/LICENSE
autopretorch-0.1.0.dist-info/METADATA
autopretorch-0.1.0.dist-info/WHEEL
autopretorch-0.1.0.dist-info/top_level.txt
autopretorch-0.1.0.dist-info/RECORD
