Metadata-Version: 2.4
Name: autopretorch
Version: 0.1.0
Summary: AutoPreTorch - extended preprocessing library for PyTorch
Author: Your Name
Requires-Python: >=3.8
License-File: LICENSE
Requires-Dist: torch
Requires-Dist: pandas
Requires-Dist: numpy
Requires-Dist: scikit-learn
Requires-Dist: joblib
Dynamic: author
Dynamic: license-file
Dynamic: requires-dist
Dynamic: requires-python
Dynamic: summary
